{"display_name":"PapierMacheTV","_id":88405531,"name":"papiermachetv","type":"user","bio":"I studied Computer Science at UC Berkeley and was born in Beverly Glen, CA. I've been to Hawaii and Jamaica. I currently reside in Los Angeles, CA. I grew up playing Counter-Strike in the SoCal LAN scene.","created_at":"2015-04-12T23:59:06Z","updated_at":"2016-11-16T03:01:57Z","logo":"https://static-cdn.jtvnw.net/jtv_user_pictures/papiermachetv-profile_image-3f06c2d9f0b58ecb-300x300.jpeg","_links":{"self":"https://api.twitch.tv/kraken/users/papiermachetv"}}